__init__.py
orpheus/__init__.py
orpheus/_vendor/__init__.py
orpheus/_vendor/lime/__init__.py
orpheus/_vendor/lime/bundle.js
orpheus/_vendor/lime/discretize.py
orpheus/_vendor/lime/exceptions.py
orpheus/_vendor/lime/explanation.py
orpheus/_vendor/lime/lime_base.py
orpheus/_vendor/lime/lime_image.py
orpheus/_vendor/lime/lime_tabular.py
orpheus/_vendor/lime/lime_text.py
orpheus/_vendor/lime/submodular_pick.py
orpheus/_vendor/lime/webpack.config.js
orpheus/_vendor/lime/tests/__init__.py
orpheus/_vendor/lime/tests/test_discretize.py
orpheus/_vendor/lime/tests/test_generic_utils.py
orpheus/_vendor/lime/tests/test_lime_tabular.py
orpheus/_vendor/lime/tests/test_lime_text.py
orpheus/_vendor/lime/tests/test_scikit_image.py
orpheus/_vendor/lime/utils/__init__.py
orpheus/_vendor/lime/utils/generic_utils.py
orpheus/_vendor/lime/wrappers/__init__.py
orpheus/_vendor/lime/wrappers/scikit_image.py
orpheus/components/__init__.py
orpheus/components/hypertuner/__init__.py
orpheus/components/hypertuner/hypertuner.py
orpheus/components/hypertuner/hypertuner_stacked.py
orpheus/components/hypertuner/utils/__init__.py
orpheus/components/hypertuner/utils/custom_types.py
orpheus/components/hypertuner/utils/helper_functions.py
orpheus/components/libs/__init__.py
orpheus/components/libs/_base.py
orpheus/components/libs/config_manager.py
orpheus/components/libs/predict_object.py
orpheus/components/preprocessing/__init__.py
orpheus/components/preprocessing/constants.py
orpheus/components/preprocessing/downcasting.py
orpheus/components/preprocessing/feature_adding.py
orpheus/components/preprocessing/feature_removing.py
orpheus/components/preprocessing/scaling.py
orpheus/components/preprocessing/tests/__init__.py
orpheus/components/preprocessing/tests/tests_downcasting.py
orpheus/components/preprocessing/tests/tests_feature_adding.py
orpheus/components/preprocessing/tests/tests_scaling.py
orpheus/evaluators/__init__.py
orpheus/evaluators/evaluator.py
orpheus/evaluators/model_evaluators.py
orpheus_ml-1.3.13.dist-info/LICENSE
orpheus_ml-1.3.13.dist-info/METADATA
orpheus_ml-1.3.13.dist-info/WHEEL
orpheus_ml-1.3.13.dist-info/top_level.txt
orpheus_ml-1.3.13.dist-info/RECORD
