Metadata-Version: 2.1
Name: orpheus-ml
Version: 1.3.13
Summary: A package for automated ML model training and creation of pipelines capable of handling multiple estimators.
Author: Vincent Ouwendijk
License: All Rights Reserved
Requires-Python: <3.12,>=3.8
License-File: LICENSE
Requires-Dist: numpy <2,>=1.24.1
Requires-Dist: pandas <3,>=1.5.2
Requires-Dist: scikit-learn <2,>=1.2.0
Requires-Dist: matplotlib <4,>=3.6.3
Requires-Dist: joblib <2,>=1.2
Requires-Dist: xgboost <3,>=2
Requires-Dist: featuretools ==1.28.0
Requires-Dist: schema ==0.7.5
Requires-Dist: ruamel.yaml ==0.17.21
Requires-Dist: bayesian-optimization ==1.4.2
Requires-Dist: setuptools-scm >=8
Requires-Dist: setuptools >=64
Provides-Extra: dev
Requires-Dist: ruff >=0.0.90 ; extra == 'dev'
Requires-Dist: black ==22.3.0 ; extra == 'dev'
Requires-Dist: pytest >=6.0 ; extra == 'dev'
Requires-Dist: isort ==5.13.2 ; extra == 'dev'
Requires-Dist: autoflake ==2.3.1 ; extra == 'dev'
